<annotation verified="yes">
	<folder>kepekadatbazis</folder>
	<filename>123.jpg</filename>
	<path>E:\mentes\bme\MSC\3\Deeplearning\nagyhazi\kepekadatbazis\123.jpg</path>
	<source>
		<database>Unknown</database>
	</source>
	<size>
		<width>1200</width>
		<height>1800</height>
		<depth>3</depth>
	</size>
	<segmented>0</segmented>
	<object>
		<name>mole</name>
		<pose>Unspecified</pose>
		<truncated>0</truncated>
		<difficult>0</difficult>
		<bndbox>
			<xmin>426</xmin>
			<ymin>275</ymin>
			<xmax>469</xmax>
			<ymax>325</ymax>
		</bndbox>
	</object>
	<object>
		<name>mole</name>
		<pose>Unspecified</pose>
		<truncated>0</truncated>
		<difficult>0</difficult>
		<bndbox>
			<xmin>659</xmin>
			<ymin>232</ymin>
			<xmax>698</xmax>
			<ymax>277</ymax>
		</bndbox>
	</object>
	<object>
		<name>mole</name>
		<pose>Unspecified</pose>
		<truncated>0</truncated>
		<difficult>0</difficult>
		<bndbox>
			<xmin>769</xmin>
			<ymin>311</ymin>
			<xmax>800</xmax>
			<ymax>348</ymax>
		</bndbox>
	</object>
	<object>
		<name>mole</name>
		<pose>Unspecified</pose>
		<truncated>0</truncated>
		<difficult>0</difficult>
		<bndbox>
			<xmin>898</xmin>
			<ymin>402</ymin>
			<xmax>938</xmax>
			<ymax>440</ymax>
		</bndbox>
	</object>
	<object>
		<name>mole</name>
		<pose>Unspecified</pose>
		<truncated>0</truncated>
		<difficult>0</difficult>
		<bndbox>
			<xmin>713</xmin>
			<ymin>688</ymin>
			<xmax>763</xmax>
			<ymax>730</ymax>
		</bndbox>
	</object>
	<object>
		<name>mole</name>
		<pose>Unspecified</pose>
		<truncated>0</truncated>
		<difficult>0</difficult>
		<bndbox>
			<xmin>450</xmin>
			<ymin>859</ymin>
			<xmax>490</xmax>
			<ymax>904</ymax>
		</bndbox>
	</object>
	<object>
		<name>mole</name>
		<pose>Unspecified</pose>
		<truncated>0</truncated>
		<difficult>0</difficult>
		<bndbox>
			<xmin>251</xmin>
			<ymin>915</ymin>
			<xmax>303</xmax>
			<ymax>955</ymax>
		</bndbox>
	</object>
	<object>
		<name>mole</name>
		<pose>Unspecified</pose>
		<truncated>0</truncated>
		<difficult>0</difficult>
		<bndbox>
			<xmin>228</xmin>
			<ymin>1013</ymin>
			<xmax>271</xmax>
			<ymax>1050</ymax>
		</bndbox>
	</object>
	<object>
		<name>mole</name>
		<pose>Unspecified</pose>
		<truncated>0</truncated>
		<difficult>0</difficult>
		<bndbox>
			<xmin>607</xmin>
			<ymin>1023</ymin>
			<xmax>644</xmax>
			<ymax>1073</ymax>
		</bndbox>
	</object>
	<object>
		<name>mole</name>
		<pose>Unspecified</pose>
		<truncated>0</truncated>
		<difficult>0</difficult>
		<bndbox>
			<xmin>536</xmin>
			<ymin>1282</ymin>
			<xmax>575</xmax>
			<ymax>1336</ymax>
		</bndbox>
	</object>
	<object>
		<name>mole</name>
		<pose>Unspecified</pose>
		<truncated>0</truncated>
		<difficult>0</difficult>
		<bndbox>
			<xmin>936</xmin>
			<ymin>1159</ymin>
			<xmax>965</xmax>
			<ymax>1192</ymax>
		</bndbox>
	</object>
	<object>
		<name>mole</name>
		<pose>Unspecified</pose>
		<truncated>0</truncated>
		<difficult>0</difficult>
		<bndbox>
			<xmin>986</xmin>
			<ymin>1175</ymin>
			<xmax>1023</xmax>
			<ymax>1213</ymax>
		</bndbox>
	</object>
	<object>
		<name>mole</name>
		<pose>Unspecified</pose>
		<truncated>0</truncated>
		<difficult>0</difficult>
		<bndbox>
			<xmin>957</xmin>
			<ymin>1338</ymin>
			<xmax>1007</xmax>
			<ymax>1392</ymax>
		</bndbox>
	</object>
	<object>
		<name>mole</name>
		<pose>Unspecified</pose>
		<truncated>0</truncated>
		<difficult>0</difficult>
		<bndbox>
			<xmin>734</xmin>
			<ymin>1219</ymin>
			<xmax>780</xmax>
			<ymax>1259</ymax>
		</bndbox>
	</object>
	<object>
		<name>mole</name>
		<pose>Unspecified</pose>
		<truncated>0</truncated>
		<difficult>0</difficult>
		<bndbox>
			<xmin>665</xmin>
			<ymin>1394</ymin>
			<xmax>707</xmax>
			<ymax>1432</ymax>
		</bndbox>
	</object>
	<object>
		<name>mole</name>
		<pose>Unspecified</pose>
		<truncated>0</truncated>
		<difficult>0</difficult>
		<bndbox>
			<xmin>1046</xmin>
			<ymin>1588</ymin>
			<xmax>1084</xmax>
			<ymax>1627</ymax>
		</bndbox>
	</object>
	<object>
		<name>mole</name>
		<pose>Unspecified</pose>
		<truncated>0</truncated>
		<difficult>0</difficult>
		<bndbox>
			<xmin>1086</xmin>
			<ymin>1525</ymin>
			<xmax>1136</xmax>
			<ymax>1559</ymax>
		</bndbox>
	</object>
	<object>
		<name>mole</name>
		<pose>Unspecified</pose>
		<truncated>0</truncated>
		<difficult>0</difficult>
		<bndbox>
			<xmin>1013</xmin>
			<ymin>454</ymin>
			<xmax>1051</xmax>
			<ymax>482</ymax>
		</bndbox>
	</object>
	<object>
		<name>mole</name>
		<pose>Unspecified</pose>
		<truncated>0</truncated>
		<difficult>0</difficult>
		<bndbox>
			<xmin>378</xmin>
			<ymin>94</ymin>
			<xmax>419</xmax>
			<ymax>121</ymax>
		</bndbox>
	</object>
	<object>
		<name>mole</name>
		<pose>Unspecified</pose>
		<truncated>0</truncated>
		<difficult>0</difficult>
		<bndbox>
			<xmin>234</xmin>
			<ymin>365</ymin>
			<xmax>280</xmax>
			<ymax>404</ymax>
		</bndbox>
	</object>
	<object>
		<name>mole</name>
		<pose>Unspecified</pose>
		<truncated>0</truncated>
		<difficult>0</difficult>
		<bndbox>
			<xmin>600</xmin>
			<ymin>800</ymin>
			<xmax>640</xmax>
			<ymax>854</ymax>
		</bndbox>
	</object>
	<object>
		<name>mole</name>
		<pose>Unspecified</pose>
		<truncated>0</truncated>
		<difficult>0</difficult>
		<bndbox>
			<xmin>955</xmin>
			<ymin>721</ymin>
			<xmax>984</xmax>
			<ymax>754</ymax>
		</bndbox>
	</object>
	<object>
		<name>mole</name>
		<pose>Unspecified</pose>
		<truncated>0</truncated>
		<difficult>0</difficult>
		<bndbox>
			<xmin>723</xmin>
			<ymin>919</ymin>
			<xmax>771</xmax>
			<ymax>969</ymax>
		</bndbox>
	</object>
	<object>
		<name>mole</name>
		<pose>Unspecified</pose>
		<truncated>0</truncated>
		<difficult>0</difficult>
		<bndbox>
			<xmin>434</xmin>
			<ymin>1246</ymin>
			<xmax>476</xmax>
			<ymax>1279</ymax>
		</bndbox>
	</object>
	<object>
		<name>mole</name>
		<pose>Unspecified</pose>
		<truncated>0</truncated>
		<difficult>0</difficult>
		<bndbox>
			<xmin>842</xmin>
			<ymin>425</ymin>
			<xmax>882</xmax>
			<ymax>465</ymax>
		</bndbox>
	</object>
	<object>
		<name>mole</name>
		<pose>Unspecified</pose>
		<truncated>0</truncated>
		<difficult>0</difficult>
		<bndbox>
			<xmin>1144</xmin>
			<ymin>411</ymin>
			<xmax>1182</xmax>
			<ymax>454</ymax>
		</bndbox>
	</object>
	<object>
		<name>mole</name>
		<pose>Unspecified</pose>
		<truncated>0</truncated>
		<difficult>0</difficult>
		<bndbox>
			<xmin>753</xmin>
			<ymin>150</ymin>
			<xmax>794</xmax>
			<ymax>180</ymax>
		</bndbox>
	</object>
	<object>
		<name>mole</name>
		<pose>Unspecified</pose>
		<truncated>0</truncated>
		<difficult>0</difficult>
		<bndbox>
			<xmin>471</xmin>
			<ymin>130</ymin>
			<xmax>507</xmax>
			<ymax>159</ymax>
		</bndbox>
	</object>
	<object>
		<name>mole</name>
		<pose>Unspecified</pose>
		<truncated>0</truncated>
		<difficult>0</difficult>
		<bndbox>
			<xmin>521</xmin>
			<ymin>188</ymin>
			<xmax>557</xmax>
			<ymax>219</ymax>
		</bndbox>
	</object>
	<object>
		<name>mole</name>
		<pose>Unspecified</pose>
		<truncated>0</truncated>
		<difficult>0</difficult>
		<bndbox>
			<xmin>444</xmin>
			<ymin>96</ymin>
			<xmax>478</xmax>
			<ymax>132</ymax>
		</bndbox>
	</object>
	<object>
		<name>mole</name>
		<pose>Unspecified</pose>
		<truncated>0</truncated>
		<difficult>0</difficult>
		<bndbox>
			<xmin>294</xmin>
			<ymin>638</ymin>
			<xmax>330</xmax>
			<ymax>680</ymax>
		</bndbox>
	</object>
	<object>
		<name>mole</name>
		<pose>Unspecified</pose>
		<truncated>0</truncated>
		<difficult>0</difficult>
		<bndbox>
			<xmin>488</xmin>
			<ymin>1448</ymin>
			<xmax>525</xmax>
			<ymax>1488</ymax>
		</bndbox>
	</object>
	<object>
		<name>mole</name>
		<pose>Unspecified</pose>
		<truncated>0</truncated>
		<difficult>0</difficult>
		<bndbox>
			<xmin>609</xmin>
			<ymin>1534</ymin>
			<xmax>648</xmax>
			<ymax>1567</ymax>
		</bndbox>
	</object>
	<object>
		<name>mole</name>
		<pose>Unspecified</pose>
		<truncated>0</truncated>
		<difficult>0</difficult>
		<bndbox>
			<xmin>398</xmin>
			<ymin>1563</ymin>
			<xmax>440</xmax>
			<ymax>1602</ymax>
		</bndbox>
	</object>
	<object>
		<name>mole</name>
		<pose>Unspecified</pose>
		<truncated>0</truncated>
		<difficult>0</difficult>
		<bndbox>
			<xmin>121</xmin>
			<ymin>1052</ymin>
			<xmax>159</xmax>
			<ymax>1090</ymax>
		</bndbox>
	</object>
	<object>
		<name>mole</name>
		<pose>Unspecified</pose>
		<truncated>0</truncated>
		<difficult>0</difficult>
		<bndbox>
			<xmin>446</xmin>
			<ymin>915</ymin>
			<xmax>475</xmax>
			<ymax>952</ymax>
		</bndbox>
	</object>
	<object>
		<name>mole</name>
		<pose>Unspecified</pose>
		<truncated>0</truncated>
		<difficult>0</difficult>
		<bndbox>
			<xmin>371</xmin>
			<ymin>863</ymin>
			<xmax>407</xmax>
			<ymax>904</ymax>
		</bndbox>
	</object>
</annotation>
